gcp_flowlogs_reader/__init__.py
gcp_flowlogs_reader/__main__.py
gcp_flowlogs_reader/aggregation.py
gcp_flowlogs_reader/gcp_flowlogs_reader.py
gcp_flowlogs_reader-3.0.0.dist-info/LICENSE
gcp_flowlogs_reader-3.0.0.dist-info/METADATA
gcp_flowlogs_reader-3.0.0.dist-info/WHEEL
gcp_flowlogs_reader-3.0.0.dist-info/entry_points.txt
gcp_flowlogs_reader-3.0.0.dist-info/top_level.txt
gcp_flowlogs_reader-3.0.0.dist-info/RECORD
